LICENSE.txt
MANIFEST.in
README.rst
requirements.core.txt
requirements.txt
setup.py
core_visualization_app/__init__.py
core_visualization_app/admin.py
core_visualization_app/apps.py
core_visualization_app/menus.py
core_visualization_app/models.py
core_visualization_app/settings.py
core_visualization_app/tasks.py
core_visualization_app/urls.py
core_visualization_app.egg-info/PKG-INFO
core_visualization_app.egg-info/SOURCES.txt
core_visualization_app.egg-info/dependency_links.txt
core_visualization_app.egg-info/requires.txt
core_visualization_app.egg-info/top_level.txt
core_visualization_app/components/__init__.py
core_visualization_app/components/category/__init__.py
core_visualization_app/components/category/api.py
core_visualization_app/components/category/models.py
core_visualization_app/components/category/operations.py
core_visualization_app/components/tests/__init__.py
core_visualization_app/components/visualization_configuration/__init__.py
core_visualization_app/components/visualization_configuration/api.py
core_visualization_app/components/visualization_configuration/models.py
core_visualization_app/components/visualization_configuration/operations.py
core_visualization_app/components/visualization_data/__init__.py
core_visualization_app/components/visualization_data/api.py
core_visualization_app/components/visualization_data/models.py
core_visualization_app/components/visualization_data/operations.py
core_visualization_app/permissions/__init__.py
core_visualization_app/permissions/discover.py
core_visualization_app/permissions/rights.py
core_visualization_app/static/core_visualization_app/admin/js/build_visualization_data.js
core_visualization_app/static/core_visualization_app/user/img/pieChartExample.png
core_visualization_app/static/core_visualization_app/user/js/download_data_table.js
core_visualization_app/static/core_visualization_app/user/js/load_data_table.js
core_visualization_app/static/core_visualization_app/user/js/load_data_table.raw.js
core_visualization_app/static/core_visualization_app/user/js/select_category_form.js
core_visualization_app/static/core_visualization_app/user/js/select_category_form.raw.js
