Metadata-Version: 2.1
Name: core-visualization-app
Version: 1.4.1
Summary: Visualization app
Home-page: https://github.com/usnistgov/core_visualization_app
Author: NIST IT Lab
Author-email: itl_inquiries@nist.gov
License: UNKNOWN
Platform: UNKNOWN
License-File: LICENSE.txt
